pylibdmtx/__init__.py
pylibdmtx/dmtx_library.py
pylibdmtx/pylibdmtx.py
pylibdmtx/pylibdmtx_error.py
pylibdmtx/wrapper.py
pylibdmtx/scripts/__init__.py
pylibdmtx/scripts/read_datamatrix.py
pylibdmtx/scripts/write_datamatrix.py
pylibdmtx/tests/__init__.py
pylibdmtx/tests/datamatrix.png
pylibdmtx/tests/empty.png
pylibdmtx/tests/test_dmtx_library.py
pylibdmtx/tests/test_pylibdmtx.py
pylibdmtx/tests/test_read_write_datamatrix.py
pylibdmtx-0.1.9.data/scripts/read_datamatrix.py
pylibdmtx-0.1.9.data/scripts/write_datamatrix.py
pylibdmtx-0.1.9.dist-info/LICENSE.txt
pylibdmtx-0.1.9.dist-info/METADATA
pylibdmtx-0.1.9.dist-info/WHEEL
pylibdmtx-0.1.9.dist-info/entry_points.txt
pylibdmtx-0.1.9.dist-info/top_level.txt
pylibdmtx-0.1.9.dist-info/RECORD
